unstructured_platform_plugins/__init__.py
unstructured_platform_plugins/__version__.py
unstructured_platform_plugins/type_hints.py
unstructured_platform_plugins/validate_api.py
unstructured_platform_plugins/etl_uvicorn/__init__.py
unstructured_platform_plugins/etl_uvicorn/api_generator.py
unstructured_platform_plugins/etl_uvicorn/main.py
unstructured_platform_plugins/etl_uvicorn/otel.py
unstructured_platform_plugins/etl_uvicorn/utils.py
unstructured_platform_plugins/schema/__init__.py
unstructured_platform_plugins/schema/filedata_meta.py
unstructured_platform_plugins/schema/json_schema.py
unstructured_platform_plugins/schema/model.py
unstructured_platform_plugins/schema/usage.py
unstructured_platform_plugins/schema/utils.py
unstructured_platform_plugins-0.0.41.dist-info/METADATA
unstructured_platform_plugins-0.0.41.dist-info/WHEEL
unstructured_platform_plugins-0.0.41.dist-info/entry_points.txt
unstructured_platform_plugins-0.0.41.dist-info/licenses/LICENSE.md
unstructured_platform_plugins-0.0.41.dist-info/RECORD
