Metadata-Version: 2.4
Name: unstructured_platform_plugins
Version: 0.0.41
Summary: Wrapper to convert arbitrary code into a uvicorn/fastapi implementation for Unstructured Platform
License-File: LICENSE.md
Classifier: Development Status :: 4 - Beta
Classifier: Intended Audience :: Developers
Classifier: Intended Audience :: Education
Classifier: Intended Audience :: Science/Research
Classifier: License :: OSI Approved :: Apache Software License
Classifier: Operating System :: OS Independent
Classifier: Programming Language :: Python :: 3
Classifier: Programming Language :: Python :: 3.10
Classifier: Programming Language :: Python :: 3.11
Classifier: Programming Language :: Python :: 3.12
Classifier: Programming Language :: Python :: 3.13
Classifier: Topic :: Scientific/Engineering :: Artificial Intelligence
Requires-Python: >=3.10
Requires-Dist: click
Requires-Dist: dataclasses-json
Requires-Dist: fastapi
Requires-Dist: opentelemetry-exporter-otlp-proto-grpc
Requires-Dist: opentelemetry-instrumentation-fastapi
Requires-Dist: requests
Requires-Dist: unstructured-ingest
Requires-Dist: uvicorn
